fancy_test_runners/__init__.py
fancy_test_runners/settings.py
fancy_test_runners/test_runners.py
fancy_test_runners/db/__init__.py
fancy_test_runners/db/backends/__init__.py
fancy_test_runners/db/backends/mysql/__init__.py
fancy_test_runners/db/backends/mysql/base.py
fancy_test_runners/db/backends/postgresql/__init__.py
fancy_test_runners/db/backends/postgresql/base.py
fancy_test_runners/management/__init__.py
fancy_test_runners/management/commands/__init__.py
fancy_test_runners/management/commands/test.py
django_fancy_test_runners-1.0.0.dist-info/METADATA
django_fancy_test_runners-1.0.0.dist-info/WHEEL
django_fancy_test_runners-1.0.0.dist-info/top_level.txt
django_fancy_test_runners-1.0.0.dist-info/RECORD
